zen_rule/__init__.py
zen_rule/py.typed
zen_rule/custom/__init__.py
zen_rule/custom/pyparsing_parser.py
zen_rule/custom/udf_manager.py
zen_rule-0.17.0.dist-info/METADATA
zen_rule-0.17.0.dist-info/WHEEL
zen_rule-0.17.0.dist-info/RECORD
