Metadata-Version: 2.4
Name: zen-rule
Version: 0.17.0
Summary: zen-engine enrichment for custom node spec and cache ZenDecision objects for performance
Project-URL: Homepage, https://github.com/republicroad/zen-rule
Project-URL: Documentation, https://github.com/republicroad/zen-rule/blob/main/README.md
Requires-Python: >=3.8
Requires-Dist: pyparsing>=3.1.4
Requires-Dist: zen-engine
